LICENSE
argsearch/__init__.py
argsearch/commands.py
argsearch/interface.py
argsearch/optimization.py
argsearch/ranges.py
argsearch/strategies.py
argsearch-0.3.0.dist-info/entry_points.txt
argsearch-0.3.0.dist-info/LICENSE
argsearch-0.3.0.dist-info/WHEEL
argsearch-0.3.0.dist-info/METADATA
argsearch-0.3.0.dist-info/RECORD
