Metadata-Version: 2.1
Name: argsearch
Version: 0.3.0
Summary: Run a command many times with different combinations of its inputs.
Home-page: https://github.com/maxwells-daemons/argsearch
License: MIT
Keywords: search,cli
Author: Aidan Swope
Author-email: aidanswope@gmail.com
Maintainer: Aidan Swope
Maintainer-email: aidanswope@gmail.com
Requires-Python: >=3.6,<4.0
Classifier: Environment :: Console
Classifier: License :: OSI Approved :: MIT License
Classifier: Programming Language :: Python :: 3
Classifier: Programming Language :: Python :: 3.6
Classifier: Programming Language :: Python :: 3.7
Classifier: Programming Language :: Python :: 3.8
Classifier: Topic :: System :: Shells
Classifier: Topic :: Terminals
Classifier: Topic :: Utilities
Requires-Dist: numpy (>=1.19.1,<2.0.0)
Requires-Dist: scikit-optimize (>=0.8.1,<0.9.0)
Requires-Dist: scipy (>=1.5.2,<2.0.0)
Requires-Dist: sobol_seq (>=0.2.0,<0.3.0)
Requires-Dist: tqdm (>=4.49.0,<5.0.0)
Project-URL: Repository, https://github.com/maxwells-daemons/argsearch
